signed_xmlrpc/__init__.py
signed_xmlrpc/client.py
signed_xmlrpc/exceptions.py
signed_xmlrpc/server.py
signed_xmlrpc-0.0.1.dist-info/LICENSE
signed_xmlrpc-0.0.1.dist-info/METADATA
signed_xmlrpc-0.0.1.dist-info/WHEEL
signed_xmlrpc-0.0.1.dist-info/top_level.txt
signed_xmlrpc-0.0.1.dist-info/RECORD
