Metadata-Version: 2.1
Name: signed-xmlrpc
Version: 0.0.1
Summary: xml rpc library for sending signed data
Home-page: https://github.com/manfred-kaiser/signed-xmlrpc
Author: Manfred Kaiser
Author-email: manfred.kaiser@logfile.at
License: UNKNOWN
Platform: UNKNOWN
Classifier: Programming Language :: Python :: 3
Classifier: License :: OSI Approved :: GNU General Public License v3 (GPLv3)
Classifier: Topic :: System :: Networking
Requires-Dist: ecdsa
